AUTHORS
ChangeLog
LICENSE
MANIFEST.in
README.md
demo.py
requirements.txt
setup.cfg
setup.py
tremendous/__init__.py
tremendous/api.py
tremendous/bindings.py
tremendous/colors.py
tremendous/ext.py
tremendous/twofifty.py
tremendous.egg-info/PKG-INFO
tremendous.egg-info/SOURCES.txt
tremendous.egg-info/dependency_links.txt
tremendous.egg-info/not-zip-safe
tremendous.egg-info/requires.txt
tremendous.egg-info/top_level.txt
tremendous/libfab/.gitignore
tremendous/libfab/LICENSE
tremendous/libfab/Makefile
tremendous/libfab/README.md
tremendous/libfab/Tupfile
tremendous/libfab/include/fab.h
tremendous/libfab/src/fab.c