Metadata-Version: 1.1
Name: tremendous
Version: 0.0.1
Summary: Python bindings to libfab (C), a reimplementation of fabulous
Home-page: UNKNOWN
Author: Ryan S. Brown
Author-email: sb@ryansb.com
License: MIT
Keywords: fabulous
Platform: UNKNOWN
Classifier: Natural Language :: English
Classifier: Operating System :: POSIX :: Linux
Classifier: Programming Language :: Python :: 2.7
Classifier: Programming Language :: Python :: 3.3
